protein_glm/__init__.py
protein_glm/protein_glm.py
protein_glm-0.0.2.dist-info/LICENSE
protein_glm-0.0.2.dist-info/METADATA
protein_glm-0.0.2.dist-info/WHEEL
protein_glm-0.0.2.dist-info/top_level.txt
protein_glm-0.0.2.dist-info/RECORD
