Metadata-Version: 2.1
Name: protein-glm
Version: 0.0.2
Summary: Protein generative model with General Language Model PreTraining (GLM)
Home-page: https://github.com/lucidrains/protein-glm
Author: Phil Wang
Author-email: lucidrains@gmail.com
License: MIT
Keywords: artificial intelligence,deep learning,transformers,attention mechanism,proteins
Platform: UNKNOWN
Classifier: Development Status :: 4 - Beta
Classifier: Intended Audience :: Developers
Classifier: Topic :: Scientific/Engineering :: Artificial Intelligence
Classifier: License :: OSI Approved :: MIT License
Classifier: Programming Language :: Python :: 3.6
License-File: LICENSE
Requires-Dist: einops (>=0.4)
Requires-Dist: torch (>=1.6)
